FileManager-1.0.12.dist-info/DESCRIPTION.rst
FileManager-1.0.12.dist-info/METADATA
FileManager-1.0.12.dist-info/RECORD
FileManager-1.0.12.dist-info/WHEEL
FileManager-1.0.12.dist-info/metadata.json
FileManager-1.0.12.dist-info/top_level.txt
filemanager/__init__.py
filemanager/methods.py
