Metadata-Version: 2.0
Name: FileManager
Version: 1.0.12
Summary: 
Home-page: https://github.com/JaineBudke
Author: Jaine Budke
Author-email: jainebudke@hotmail.com
License: MIT
Keywords: bioinformatics neuroscience
Platform: UNKNOWN
Classifier: Development Status :: 1 - Planning
Classifier: Intended Audience :: Developers
Classifier: Topic :: Software Development :: Build Tools
Classifier: Intended Audience :: Science/Research
Classifier: Topic :: Scientific/Engineering :: Bio-Informatics
Classifier: License :: OSI Approved :: Academic Free License (AFL)
Classifier: Programming Language :: Python
Classifier: Programming Language :: Python :: 3
Requires-Dist: lockfile (>=0.12)
Requires-Dist: sh (>=1.11)
